{
  "label": "7Climb",
  "packageName": "io.github.climbintelligence",
  "latestApkUrl": "https://github.com/yrkan/7climb/releases/latest/download/7climb.apk",
  "latestVersion": "1.0.1",
  "latestVersionCode": 2,
  "iconUrl": "https://raw.githubusercontent.com/yrkan/7climb/main/assets/icon.png",
  "developer": "Yuri Kan",
  "description": "Real-time climb intelligence for Hammerhead Karoo. W' Balance tracking (Skiba model), physics-based pacing, automatic climb detection, PR comparison, and 9 specialized data fields — all updating at 1Hz.",
  "releaseNotes": "v1.0.1: Remove unused vibration support (Karoo has no vibration motor), clean up alerts.",
  "screenshotUrls": [
    "https://raw.githubusercontent.com/yrkan/7climb/main/screenshots/1.png",
    "https://raw.githubusercontent.com/yrkan/7climb/main/screenshots/2.png",
    "https://raw.githubusercontent.com/yrkan/7climb/main/screenshots/3.png",
    "https://raw.githubusercontent.com/yrkan/7climb/main/screenshots/4.png",
    "https://raw.githubusercontent.com/yrkan/7climb/main/screenshots/5.png",
    "https://raw.githubusercontent.com/yrkan/7climb/main/screenshots/6.png",
    "https://raw.githubusercontent.com/yrkan/7climb/main/screenshots/7.png",
    "https://raw.githubusercontent.com/yrkan/7climb/main/screenshots/8.png",
    "https://raw.githubusercontent.com/yrkan/7climb/main/screenshots/9.png",
    "https://raw.githubusercontent.com/yrkan/7climb/main/screenshots/10.png"
  ]
}
